README.txt
setup.py
brackets/__init__.py
brackets/compile.py
brackets/exceptions.py
brackets/helpers.py
brackets/importer.py
brackets/runtime.py
brackets/shell.py
brackets/translate.py
brackets.egg-info/PKG-INFO
brackets.egg-info/SOURCES.txt
brackets.egg-info/dependency_links.txt
brackets.egg-info/entry_points.txt
brackets.egg-info/requires.txt
brackets.egg-info/top_level.txt
brackets/tests/__init__.py
brackets/tests/with_codecs.py
brackets/tests/with_importer.bpy