Metadata-Version: 1.1
Name: brackets
Version: 0.6.2
Summary: Use curly braces instead of indenting, plus much more sugar added to Python's syntax.
Home-page: http://python-brackets.org
Author: Pooya Eghbali
Author-email: persian.writer@gmail.com
License: BSD
Keywords: brackets,indentation,indent,indenting,parser,encoding
Platform: Any
Classifier: Intended Audience :: Developers
Classifier: License :: OSI Approved :: BSD License
Classifier: Operating System :: OS Independent
Classifier: Programming Language :: Python :: 3
